sanic_discord/__init__.py
sanic_discord/py.typed
sanic_discord/interaction/__init__.py
sanic_discord/interaction/client.py
sanic_discord/interaction/errors.py
sanic_discord/interaction/http.py
sanic_discord/oauth/__init__.py
sanic_discord/oauth/access_token.py
sanic_discord/oauth/blueprints.py
sanic_discord/oauth/errors.py
sanic_discord/oauth/http.py
sanic_discord/oauth/oauth.py
sanic_discord/rest/__init__.py
sanic_discord/rest/errors.py
sanic_discord/rest/rest.py
sanic_discord-2.0.1.dist-info/METADATA
sanic_discord-2.0.1.dist-info/WHEEL
sanic_discord-2.0.1.dist-info/top_level.txt
sanic_discord-2.0.1.dist-info/RECORD
