Metadata-Version: 2.1
Name: sanic-discord
Version: 2.0.1
Summary: Sanic Discord OAuth2 and Interaction
Home-page: https://github.com/tuna2134/sanic-discord
Author: tuna2134
Author-email: support@mc-fdc.live
License: MIT
Classifier: Development Status :: 5 - Production/Stable
Classifier: Intended Audience :: Developers
Classifier: License :: OSI Approved :: MIT License
Classifier: Programming Language :: Python :: 3.8
Classifier: Programming Language :: Python :: 3.9
Classifier: Programming Language :: Python :: 3.10
Classifier: Operating System :: OS Independent
Requires-Dist: httpx
Requires-Dist: sanic
Requires-Dist: PyNaCl
